dsa/__init__.py
dsa/array.py
dsa/deque.py
dsa/dijkstra.py
dsa/doublylinkedlist.py
dsa/draw.py
dsa/generators.py
dsa/graph.py
dsa/graph_traversal.py
dsa/hashset.py
dsa/hashtable.py
dsa/heap.py
dsa/huffman.py
dsa/pretty_print.py
dsa/prim.py
dsa/queue.py
dsa/singlylinkedlist.py
dsa/sorttools.py
dsa/stack.py
dsa/tree.py
dsa/trie.py
ucxdsa-2025.12.24.dist-info/METADATA
ucxdsa-2025.12.24.dist-info/WHEEL
ucxdsa-2025.12.24.dist-info/licenses/LICENSE
ucxdsa-2025.12.24.dist-info/RECORD
