Metadata-Version: 2.4
Name: ucxdsa
Version: 2025.12.24
Summary: Data Structures and Algorithms Source Code
Project-URL: Homepage, https://github.com/ucxinstructor/dsa_package
Author-email: Carl Limsico <limsico@berkeley.edu>
License-Expression: MIT
License-File: LICENSE
Classifier: License :: OSI Approved :: MIT License
Classifier: Operating System :: OS Independent
Classifier: Programming Language :: Python :: 3
Requires-Python: >=3.7
Requires-Dist: matplotlib
Requires-Dist: networkx
